python_ntpclient/__init__.py
python_ntpclient-0.0.2.dist-info/METADATA
python_ntpclient-0.0.2.dist-info/WHEEL
python_ntpclient-0.0.2.dist-info/top_level.txt
python_ntpclient-0.0.2.dist-info/RECORD
