Metadata-Version: 2.4
Name: python-ntpclient
Version: 0.0.2
Summary: An academic experiment package
Home-page: https://pypi.org/project/django-dynamic-formset/
Author: Guangye Bai
Author-email: 2253637@tongji.edu.cn
License: MIT
Keywords: ,ntpclient,python-ntpclient,typosquatting,security
Classifier: Development Status :: 2 - Pre-Alpha
Classifier: Intended Audience :: Developers
Classifier: License :: OSI Approved :: MIT License
Classifier: Programming Language :: Python :: 3
Classifier: Topic :: Software Development :: Libraries
Requires-Python: >=3.6
Dynamic: author
Dynamic: author-email
Dynamic: classifier
Dynamic: description
Dynamic: description-content-type
Dynamic: home-page
Dynamic: keywords
Dynamic: license
Dynamic: requires-python
Dynamic: summary
